mcp_server_windbg/__init__.py
mcp_server_windbg/__main__.py
mcp_server_windbg/cdb_session.py
mcp_server_windbg/server.py
mcp_server_windbg/tests/test_cdb.py
mcp_server_windbg/tests/test_remote_debugging.py
mseep_mcp_server_windbg-0.1.1.dist-info/licenses/LICENSE
mseep_mcp_server_windbg-0.1.1.dist-info/METADATA
mseep_mcp_server_windbg-0.1.1.dist-info/WHEEL
mseep_mcp_server_windbg-0.1.1.dist-info/entry_points.txt
mseep_mcp_server_windbg-0.1.1.dist-info/top_level.txt
mseep_mcp_server_windbg-0.1.1.dist-info/RECORD
