Metadata-Version: 2.4
Name: mseep-mcp-server-windbg
Version: 0.1.1
Summary: A Model Context Protocol server providing tools to analyze Windows crash dumps using WinDBG/CDB
Author-email: mseep <support@skydeck.ai>
License: MIT
Keywords: windbg,cdb,mcp,llm,crash-analysis
Classifier: Development Status :: 4 - Beta
Classifier: Intended Audience :: Developers
Classifier: License :: OSI Approved :: MIT License
Classifier: Programming Language :: Python :: 3
Classifier: Programming Language :: Python :: 3.10
Requires-Python: >=3.10
License-File: LICENSE
Requires-Dist: mcp>=1.1.3
Requires-Dist: pydantic>=2.0.0
Provides-Extra: test
Requires-Dist: pytest>=7.0.0; extra == "test"
Dynamic: license-file
